divi/__init__.py
divi/utils.py
divi/decorators/__init__.py
divi/decorators/collect.py
divi/decorators/obs_openai.py
divi/decorators/observable.py
divi/decorators/observe.py
divi/evaluation/__init__.py
divi/evaluation/evaluate.py
divi/evaluation/evaluator.py
divi/evaluation/prompts.py
divi/evaluation/scores.py
divi/proto/common/v1/common.proto
divi/proto/common/v1/common_pb2.py
divi/proto/common/v1/common_pb2.pyi
divi/proto/core/health/v1/health_service.proto
divi/proto/core/health/v1/health_service_pb2.py
divi/proto/core/health/v1/health_service_pb2.pyi
divi/proto/core/health/v1/health_service_pb2_grpc.py
divi/proto/metric/v1/metric.proto
divi/proto/metric/v1/metric_pb2.py
divi/proto/metric/v1/metric_pb2.pyi
divi/proto/trace/v1/trace.proto
divi/proto/trace/v1/trace_pb2.py
divi/proto/trace/v1/trace_pb2.pyi
divi/services/__init__.py
divi/services/finish.py
divi/services/init.py
divi/services/service.py
divi/services/auth/__init__.py
divi/services/auth/auth.py
divi/services/auth/init.py
divi/services/auth/tokman.py
divi/services/core/__init__.py
divi/services/core/core.py
divi/services/core/finish.py
divi/services/core/init.py
divi/services/datapark/__init__.py
divi/services/datapark/datapark.py
divi/services/datapark/init.py
divi/session/__init__.py
divi/session/session.py
divi/session/setup.py
divi/session/teardown.py
divi/signals/__init__.py
divi/signals/span.py
divi/signals/trace.py
divi-0.0.1.dev47.dist-info/METADATA
divi-0.0.1.dev47.dist-info/WHEEL
divi-0.0.1.dev47.dist-info/licenses/LICENSE
divi-0.0.1.dev47.dist-info/RECORD
