Metadata-Version: 2.4
Name: divi
Version: 0.0.1.dev47
Summary: The Agent Platform for Observability & Evaluation
License-File: LICENSE
Requires-Python: >=3.11
Requires-Dist: grpcio>=1.71.0
Requires-Dist: openai>=1.65.2
Requires-Dist: protobuf<6.0.dev0,>=5.26.1
Requires-Dist: pyjwt>=2.10.1
Requires-Dist: requests>=2.32.3
